{"layers": [{"b_constraint": null, "name": "Dense", "activity_regularizer": null, "W_constraint": null, "input_shape": [9754], "init": "glorot_uniform", "activation": "relu", "input_dim": 9754, "b_regularizer": null, "W_regularizer": null, "output_dim": 50}, {"b_constraint": null, "name": "Dense", "activity_regularizer": null, "W_constraint": null, "input_shape": [50], "init": "glorot_uniform", "activation": "softmax", "input_dim": 50, "b_regularizer": null, "W_regularizer": null, "output_dim": 9754}], "loss": "categorical_crossentropy", "theano_mode": null, "name": "Sequential", "class_mode": "categorical", "optimizer": {"nesterov": false, "lr": 0.01, "name": "SGD", "momentum": 0.0, "decay": 0.0}}